<?xml version="1.0" encoding="UTF-8" standalone="yes"?>
<reportPackage>
    <dataLevel>offline</dataLevel>
    <files>
        <file contentKey="2YRQ6AKNSM5DPTHF25FZ4HLCIAXI2J2P" name="report" type="report">
            <links>
                <link href="/report.xml" method="GET" rel="content" type="application/vnd.sas.report.content" uri="/report.xml"/>
            </links>
        </file>
        <file contentKey="AKWA2KA55VLVTHBCNDIBFZP25IH4YNWN" name="basems1.css" type="css">
            <links>
                <link href="/css/basems1.css" method="GET" rel="content" type="text/css" uri="/css/basems1.css"/>
            </links>
        </file>
        <file contentKey="YD3UOCLHSH7QD6EEKSHKLH4ABWHV4U66" name="highcontrast.css" type="css">
            <links>
                <link href="/css/highcontrast.css" method="GET" rel="content" type="text/css" uri="/css/highcontrast.css"/>
            </links>
        </file>
        <file contentKey="5ZU3KK5KI375KP74ISD4NVTXFFCRFXRX" name="ms1.css" type="css">
            <links>
                <link href="/css/ms1.css" method="GET" rel="content" type="text/css" uri="/css/ms1.css"/>
            </links>
        </file>
        <file contentKey="TAWH3KRB7YIWPOSKPZG4EW2RI7U2WKCR" name="dd269.csv" type="data">
            <links>
                <link href="/data/dd269.csv" method="GET" rel="content" type="text/csv" uri="/data/dd269.csv"/>
            </links>
        </file>
        <file contentKey="7AUP7ARW3NU54VHVMF6L4XHD37QYXSAL" name="dd269index.csv" type="data">
            <links>
                <link href="/data/dd269index.csv" method="GET" rel="content" type="text/csv" uri="/data/dd269index.csv"/>
            </links>
        </file>
        <file contentKey="QFG6CC4E33P5KTPWOS4W6HILZ5AG74EC" name="dd36.csv" type="data">
            <links>
                <link href="/data/dd36.csv" method="GET" rel="content" type="text/csv" uri="/data/dd36.csv"/>
            </links>
        </file>
        <file contentKey="ZAXKYTB7BRSMIQPAY6QUHAVV2GGTUWEP" name="dd36index.csv" type="data">
            <links>
                <link href="/data/dd36index.csv" method="GET" rel="content" type="text/csv" uri="/data/dd36index.csv"/>
            </links>
        </file>
        <file contentKey="ZF6FFFZYRCM26ATSL7UWADTQ47B65O32" name="dd45.csv" type="data">
            <links>
                <link href="/data/dd45.csv" method="GET" rel="content" type="text/csv" uri="/data/dd45.csv"/>
            </links>
        </file>
        <file contentKey="O6MRVK5VOMSZKD6N4WZ6SRAQLL2G267Y" name="dd45index.csv" type="data">
            <links>
                <link href="/data/dd45index.csv" method="GET" rel="content" type="text/csv" uri="/data/dd45index.csv"/>
            </links>
        </file>
        <file contentKey="NKUFWNBZYK4I7PQ7ZBNRUY6JXDHEGETR" name="metadataSupplement" type="resource">
            <links>
                <link href="/metadataSupplement.xml" method="GET" rel="content" type="application/vnd.sas.report.metadata.supplement" uri="/metadataSupplement.xml"/>
            </links>
        </file>
        <file contentKey="GWBEY45BDPJKVXB6NDWN3DRW54INU6VG" name="settings" type="resource">
            <links>
                <link href="/settings.json" method="GET" rel="content" type="application/vnd.sas.attributes" uri="/settings.json"/>
            </links>
        </file>
        <file contentKey="TWKYKKVZ573DCUOKILXTSMZ22BZPAIYY" name="index.html" type="html">
            <links>
                <link href="/index.html" method="GET" rel="content" type="text/html" uri="/index.html"/>
            </links>
        </file>
        <file contentKey="XMA2HDEH2R55WEPDT4SP5H3DFQURPV3L" name="packageIndex.html" type="html">
            <links>
                <link href="/packageIndex.html" method="GET" rel="content" type="text/html" uri="/packageIndex.html"/>
            </links>
        </file>
    </files>
    <formatLocale>en-US</formatLocale>
    <generatedTimeStamp>2026-05-06T09:19:25.756Z</generatedTimeStamp>
    <id>c_90676f2f-38a1-4c3d-a290-23b0a2190a92</id>
    <links>
        <link href="/reportPackages/packages/c_90676f2f-38a1-4c3d-a290-23b0a2190a92" method="GET" rel="self" type="application/vnd.sas.report.package" uri="/reportPackages/packages/c_90676f2f-38a1-4c3d-a290-23b0a2190a92"/>
        <link href="/reportData/results?reportContentKey=AGHULYYQQQVAAJFTWBZVI7U5TKCRM2CC&amp;reportUri=%2Freports%2Freports%2F811c3000-d999-4163-b1ec-f976b4e756d7&amp;reportDate=2026-05-06T09%3A19%3A25.756Z" method="POST" rel="requery" responseType="application/vnd.sas.report.results" type="application/vnd.sas.report.query.state" uri="/reportData/results?reportContentKey=AGHULYYQQQVAAJFTWBZVI7U5TKCRM2CC&amp;reportUri=%2Freports%2Freports%2F811c3000-d999-4163-b1ec-f976b4e756d7&amp;reportDate=2026-05-06T09%3A19%3A25.756Z"/>
        <link href="/reportData/jobs?reportContentKey=AGHULYYQQQVAAJFTWBZVI7U5TKCRM2CC&amp;reportUri=%2Freports%2Freports%2F811c3000-d999-4163-b1ec-f976b4e756d7&amp;reportDate=2026-05-06T09%3A19%3A25.756Z" method="POST" rel="requeryJob" responseType="application/vnd.sas.report.data.job" type="application/vnd.sas.report.query.state" uri="/reportData/jobs?reportContentKey=AGHULYYQQQVAAJFTWBZVI7U5TKCRM2CC&amp;reportUri=%2Freports%2Freports%2F811c3000-d999-4163-b1ec-f976b4e756d7&amp;reportDate=2026-05-06T09%3A19%3A25.756Z"/>
    </links>
    <locale>en-US</locale>
    <modifiedTimeStamp>2026-05-04T14:04:11.884Z</modifiedTimeStamp>
    <reportElements>vi6</reportElements>
    <size>1223631</size>
    <source>/reports/reports/811c3000-d999-4163-b1ec-f976b4e756d7</source>
    <version>68</version>
</reportPackage>
